capdet/__init__.py
capdet/advanced_network_analyzer.py
capdet/cli.py
capdet/network_probe.py
captive_portal_detector-1.1.2.dist-info/licenses/LICENSE
captive_portal_detector-1.1.2.dist-info/METADATA
captive_portal_detector-1.1.2.dist-info/WHEEL
captive_portal_detector-1.1.2.dist-info/entry_points.txt
captive_portal_detector-1.1.2.dist-info/top_level.txt
captive_portal_detector-1.1.2.dist-info/RECORD
