Metadata-Version: 2.4
Name: captive-portal-detector
Version: 1.1.2
Summary: Detects captive portals and TLS Man-in-the-Middle attacks.
Author-email: Emilio DiTrocchio <editrocchio@gmail.com>
License-Expression: MIT
Requires-Python: >=3.7
License-File: LICENSE
Requires-Dist: requests
Requires-Dist: certifi
Requires-Dist: cryptography>=45.0.3
Requires-Dist: dnspython>=2.0
Requires-Dist: hstspreload>=2025.1.1
Requires-Dist: scapy>=2.6.1
Requires-Dist: tldextract>=5.3.0
Requires-Dist: netifaces>=0.11.0
Dynamic: license-file
